[{"name":"Andre's MMR immunization","date":"2024-05-27","time":"10:00","location":"Tehila children hospital in ph","extra_info":"","frequency":"None","id":"3034"},{"name":"Ozioma's birthday","date":"2024-09-15","time":"23:15","location":"work things on hold","extra_info":"","frequency":"None","id":"8427"},{"name":"Spa day","date":"2024-09-24","time":"17:17","location":"La belle spa","extra_info":"","frequency":"None","id":"7448"},{"name":"Random","date":"2024-03-15","time":"16:18","location":"timi's house","extra_info":"","frequency":"None","id":"3177"}]